cmdline_provenance/__init__.py
cmdline_provenance/_version.py
cmdline_provenance/cmdline_provenance.py
cmdline_provenance/test_script.py
cmdline_provenance-1.1.0.dist-info/LICENSE
cmdline_provenance-1.1.0.dist-info/METADATA
cmdline_provenance-1.1.0.dist-info/WHEEL
cmdline_provenance-1.1.0.dist-info/top_level.txt
cmdline_provenance-1.1.0.dist-info/RECORD
