Metadata-Version: 2.1
Name: cmdline_provenance
Version: 1.1.0
Summary: A Python package for keeping track of your data processing steps
Home-page: https://github.com/DamienIrving/cmdline_provenance
Author: Damien Irving
Author-email: irving.damien@gmail.com
License: MIT License
Classifier: Programming Language :: Python :: 3
Classifier: License :: OSI Approved :: MIT License
Classifier: Operating System :: OS Independent
License-File: LICENSE
Requires-Dist: ipynbname
Requires-Dist: numpy
